TrainingDataCreation.py
__init__.py
custom_t5_model.py
main.py
run.py
nikuraj006-0.0.1.dist-info/METADATA
nikuraj006-0.0.1.dist-info/WHEEL
nikuraj006-0.0.1.dist-info/RECORD
